{
  "mode": "pre",
  "tag": "alpha",
  "initialVersions": {
    "curvy": "1.0.9"
  },
  "changesets": [
    "arc-length-sampling",
    "basis-matrix-exact-sixth",
    "bezier-subdivide",
    "cardinal-options",
    "characteristic-module",
    "coincident-comparisons",
    "cubic-roots-boundary-tolerance",
    "curve-endpoint-primitives",
    "curve-solve-at",
    "dts-mts-extension",
    "dual-perf",
    "fine-foxes-pay",
    "from-api-coherence",
    "generic-path2d",
    "interval-inclusivity",
    "interval2d",
    "linear2d-spline",
    "matrix-invertible-trait",
    "matrix-relative-singularity",
    "matrix4x4-primitives",
    "module-restructure",
    "monotonicity-epsilon-tolerance",
    "path-axis-monotonicity",
    "path-solveAt-knot-fix",
    "path-uses-curve-primitives",
    "polynomial-unit-range-interval-approx",
    "precision-model",
    "punch-list",
    "quadratic-stable-roots",
    "rational-approximation",
    "rational-bezier-easing-shorthand",
    "rational-curves",
    "rational-easing-curvatures",
    "rename-curvature-aligned",
    "revert-namespace-type-reexports",
    "solution-type",
    "sour-apples-like",
    "spline-conversion-cache",
    "spline-mapPoints-flatMap",
    "svg-path-data",
    "type-level-traits",
    "vector-from-tuple",
    "vector-map-coord",
    "vector3-spherical-fix"
  ]
}
